{"id":"internal:doc-next-research-engine","kind":"design-doc","record_sha256":"adfe98805b805b372c69dd1d1a2f62c84793ddb22753339ac147bd84dc47e776","schema_version":"kot-lit-internal/1","seams":[],"source":{"path":"docs/next/research-engine.md","sha256":"aae7c992af6c60192fc42963a0babc0d39f807171979c8338210c9c4b02a8ae4"},"summary":"**Kernel of Truth programme — next-direction seed, Pillar B.** Author: Kern (Fable design agent). Date: 2026-07-08. Status: **DESIGN/PLANNING document.** No GPU spend; no registry entry is amended here. Everything proposed below becomes real only through the existing rails (`prereg-freeze` for anything that runs; maintainer sign-off for anything that changes the honesty machinery itself — P2 §7 item 3). Binding constraints: `docs/kernel-design-directives.md` (esp. §3 operationalisable-scientific","title":"N-B — The Research Engine: reusable, self-maintaining scientific-method machinery","verdict":null}
