{"id":"internal:doc-next-analysis-correctness-track-instrument-assessment","kind":"design-doc","record_sha256":"088e61b0054390da01a2e0cbdad5a4f73a0f2e3b2af227269b0ef5fbc8e3728e","schema_version":"kot-lit-internal/1","seams":[],"source":{"path":"docs/next/analysis/correctness-track-instrument-assessment.md","sha256":"eae19ed1c7891600794bfbdd48ea27b7aa873228cd52cf4bee63b626f927d347"},"summary":"**Role: Fable INTERPRETATION agent, 2026-07-12. This document assesses the repeated failure of the CORRECTNESS track's host-integration instruments — the RULES host-lift lineage (rules-1 → rules-1-b → rules-1-c) and the g2-import-v2 typing-repair pilot — against what HAS instrumented cleanly. It states NO feasibility conclusion on either thesis: that synthesis belongs to the cross-experiment feasibility node (kernel-of-truth-d8p8/m90m), and the host-integration slot decision belongs to the maint","title":"Correctness-track instrument assessment — after the fourth and fifth instrument stops (Fable)","verdict":null}
